<?xml version="1.0" encoding="UTF-8" ?>  
<!DOCTYPE generatorConfiguration PUBLIC "-//mybatis.org//DTD MyBatis Generator Configuration 1.0//EN" "http://mybatis.org/dtd/mybatis-generator-config_1_0.dtd" >
<generatorConfiguration>
	<context id="mybatis_generator">
		<commentGenerator>
			<property name="suppressDate" value="true" />
			<property name="suppressAllComments" value="true" />
		</commentGenerator>
		<jdbcConnection driverClass="org.gjt.mm.mysql.Driver"
			connectionURL="jdbc:mysql://localhost:3306/technology" userId="root"
			password="hzkjzyjsxy" />
		<javaModelGenerator targetPackage="com.entites"
			targetProject="Technology" />
		<sqlMapGenerator targetPackage="com.mapper"
			targetProject="Technology" />
		<javaClientGenerator targetPackage="com.mapper"
			targetProject="Technology" type="XMLMAPPER" />
		<!-- <table tableName="auth" enableCountByExample="false"
			enableUpdateByExample="false" enableDeleteByExample="false"
			enableSelectByExample="false" selectByExampleQueryId="false">
		</table>
		<table tableName="task" enableCountByExample="false"
			enableUpdateByExample="false" enableDeleteByExample="false"
			enableSelectByExample="false" selectByExampleQueryId="false">
		</table> -->
		<table tableName="user" enableCountByExample="false"
			enableUpdateByExample="false" enableDeleteByExample="false"
			enableSelectByExample="false" selectByExampleQueryId="false">
		</table>
		<!-- <table tableName="user" enableCountByExample="false"
			enableUpdateByExample="false" enableDeleteByExample="false"
			enableSelectByExample="false" selectByExampleQueryId="false">
		</table>
		<table tableName="user_auth" enableCountByExample="false"
			enableUpdateByExample="false" enableDeleteByExample="false"
			enableSelectByExample="false" selectByExampleQueryId="false">
		</table> -->
	</context>
</generatorConfiguration>  